customdicts/__init__.py
customdicts/__main__.py
customdicts-0.0.0.dist-info/LICENSE.txt
customdicts-0.0.0.dist-info/METADATA
customdicts-0.0.0.dist-info/WHEEL
customdicts-0.0.0.dist-info/top_level.txt
customdicts-0.0.0.dist-info/RECORD
