Metadata-Version: 2.1
Name: customdicts
Version: 0.0.0
Summary: customdicts
Author-email: Johannes <johannes-programming@posteo.org>
License: The MIT License (MIT)
Project-URL: Download, https://pypi.org/project/customdicts/#files
Project-URL: Source, https://github.com/johannes-programming/customdicts
Classifier: License :: OSI Approved :: MIT License
Classifier: Programming Language :: Python
Classifier: Programming Language :: Python :: 3
Requires-Python: >=3.11
License-File: LICENSE.txt
